{
  "annotations": {"list": []},
  "editable": true,
  "gnetId": null,
  "graphTooltip": 0,
  "links": [],
  "panels": [
    {
      "type": "stat",
      "title": "HTTP 200 count (Nginx access)",
      "targets": [
        {
          "expr": "sum by (status) (rate({job=\"docker\", stream=\"stdout\"} |= \"nginx\" |= \"\" [5m]))",
          "refId": "A",
          "datasource": {"type": "loki", "uid": "loki"}
        }
      ]
    }
  ],
  "schemaVersion": 38,
  "style": "dark",
  "tags": ["nginx"],
  "time": {"from": "now-6h", "to": "now"},
  "timezone": "",
  "title": "Nginx Overview",
  "version": 1
}
